odoo/addons/mail_activity_board/README.rst
odoo/addons/mail_activity_board/__init__.py
odoo/addons/mail_activity_board/__manifest__.py
odoo/addons/mail_activity_board/i18n/da.po
odoo/addons/mail_activity_board/i18n/fr.po
odoo/addons/mail_activity_board/i18n/it.po
odoo/addons/mail_activity_board/i18n/mail_activity_board.pot
odoo/addons/mail_activity_board/i18n/pt.po
odoo/addons/mail_activity_board/models/__init__.py
odoo/addons/mail_activity_board/models/mail_activity.py
odoo/addons/mail_activity_board/models/mail_activity_mixin.py
odoo/addons/mail_activity_board/readme/CONTRIBUTORS.rst
odoo/addons/mail_activity_board/readme/DESCRIPTION.rst
odoo/addons/mail_activity_board/readme/USAGE.rst
odoo/addons/mail_activity_board/static/description/icon.png
odoo/addons/mail_activity_board/static/description/index.html
odoo/addons/mail_activity_board/static/src/js/override_chatter.js
odoo/addons/mail_activity_board/static/src/js/systray.js
odoo/addons/mail_activity_board/static/src/xml/inherit_chatter.xml
odoo/addons/mail_activity_board/static/src/xml/systray.xml
odoo/addons/mail_activity_board/tests/__init__.py
odoo/addons/mail_activity_board/tests/test_mail_activity_board.py
odoo/addons/mail_activity_board/views/mail_activity_view.xml
odoo/addons/mail_activity_board/views/templates.xml
odoo12_addon_mail_activity_board-12.0.1.1.1.dist-info/METADATA
odoo12_addon_mail_activity_board-12.0.1.1.1.dist-info/WHEEL
odoo12_addon_mail_activity_board-12.0.1.1.1.dist-info/top_level.txt
odoo12_addon_mail_activity_board-12.0.1.1.1.dist-info/RECORD
